pycapella/__init__.py
pycapella/api.py
pycapella-0.1.6.dist-info/METADATA
pycapella-0.1.6.dist-info/RECORD
pycapella-0.1.6.dist-info/WHEEL
pycapella-0.1.6.dist-info/top_level.txt
