Metadata-Version: 2.1
Name: pycapella
Version: 0.1.6
Summary: Python SDK for capella.pics
Home-page: https://github.com/codex-team/pycapella
Author: CodeX Team
Author-email: team@ifmo.su
License: MIT
Keywords: capella image upload crop resize filter transformation manipulation cdn
Platform: UNKNOWN
Classifier: Intended Audience :: Developers
Classifier: Topic :: Software Development :: Libraries :: Python Modules
Classifier: License :: OSI Approved :: MIT License
Classifier: Programming Language :: Python
Classifier: Programming Language :: Python :: 2
Classifier: Programming Language :: Python :: 2.7
Classifier: Programming Language :: Python :: 3
Classifier: Programming Language :: Python :: 3.4
Classifier: Programming Language :: Python :: 3.5
Classifier: Programming Language :: Python :: 3.6
Classifier: Topic :: Multimedia :: Graphics
Classifier: Topic :: Multimedia :: Graphics :: Graphics Conversion
Classifier: Environment :: Console
Classifier: Environment :: Web Environment
Requires-Dist: requests
